Metadata-Version: 2.1
Name: tq010or-distributions
Version: 0.0.1rc0
Summary: This is a package for common distributions, e.g. Gaussian, Binomial
Home-page: https://github.com/tq010or/distributions
Author: Bo HAN
Author-email: bohan.academic@gmail.com
License: UNKNOWN
Platform: UNKNOWN
Classifier: Programming Language :: Python :: 3
Classifier: License :: OSI Approved :: MIT License
Classifier: Operating System :: OS Independent
Requires-Python: >=3.6
